{
  "quickReplies": [
    {
      "triggerStream": 1,
      "triggerFunction": 1,
      "conditions": [],
      "replyStream": 1,
      "replyFunction": 2,
      "replyTemplateName": "Are You There Reply",
      "description": "S1F1 -> S1F2",
      "enabled": true
    },
    {
      "triggerStream": 1,
      "triggerFunction": 13,
      "conditions": [],
      "replyStream": 1,
      "replyFunction": 14,
      "replyTemplateName": "Establish Communication Reply (ACK)",
      "description": "S1F13 -> S1F14",
      "enabled": true
    },
    {
      "triggerStream": 5,
      "triggerFunction": 1,
      "conditions": [],
      "replyStream": 5,
      "replyFunction": 2,
      "replyTemplateName": "Alarm Report Ack",
      "description": "S5F1 -> S5F2",
      "enabled": true
    },
    {
      "triggerStream": 6,
      "triggerFunction": 11,
      "conditions": [],
      "replyStream": 6,
      "replyFunction": 12,
      "replyTemplateName": "Collection Event Report Ack",
      "description": "S6F11 -> S6F12",
      "enabled": true
    }
  ],
  "scenarios": []
}
